calc/__init__.py
calc/calculator.py
calc/test_calculator.py
commondtools/__init__.py
commondtools/calc/__init__.py
commondtools/calc/calculator.py
commondtools/calc/test_calculator.py
commondtools/filehandling/__init__.py
commondtools/filehandling/csvmanager.py
commondtools/filehandling/csvreader.py
commondtools/filehandling/test_csvmanager.py
commondtools/includes/__init__.py
commondtools/includes/decorators.py
commondtools/includes/exceptions.py
commondtools/includes/oschecker.py
commondtools/network/__init__.py
commondtools/network/ping.py
commondtools/network/portscan.py
commondtools/network/validreqs.py
commondtools/parallel/__init__.py
commondtools/systemtools/__init__.py
commondtools/systemtools/beeper.py
commondtools/systemtools/environment.py
filehandling/__init__.py
filehandling/csvmanager.py
filehandling/csvreader.py
filehandling/test_csvmanager.py
network/__init__.py
network/ping.py
network/portscan.py
network/validreqs.py
parallel/__init__.py
system/__init__.py
system/environment.py
system_tools/__init__.py
system_tools/environment.py
systemtools/__init__.py
systemtools/environment.py
commondtools-0.0.26.dist-info/LICENSE
commondtools-0.0.26.dist-info/METADATA
commondtools-0.0.26.dist-info/WHEEL
commondtools-0.0.26.dist-info/top_level.txt
commondtools-0.0.26.dist-info/RECORD
